LICENSE
MANIFEST.in
README.md
setup.py
lib/action.h
lib/action_layer.h
lib/audio.h
lib/backlight.h
lib/bootloader.h
lib/config_common.h
lib/debug.h
lib/dynamic_macro.h
lib/eeconfig.h
lib/frenchdev.h
lib/i2cmaster.h
lib/keycode.h
lib/keymap.h
lib/led.h
lib/matrix.h
lib/mousekey.h
lib/outputselect.h
lib/pointing_device.h
lib/print.h
lib/process_unicode.h
lib/quantum.h
lib/quantum_keycodes.h
lib/report.h
lib/rgblight.h
lib/ssd1306.h
lib/util.h
lib/version.h
lib/LUFA/Drivers/Peripheral/TWI.h
lib/keymap_extras/keymap_bepo.h
q2k/__init__.py
q2k/core.py
q2k/gui.py
q2k/reference.py
q2k/version.py
q2k.egg-info/PKG-INFO
q2k.egg-info/SOURCES.txt
q2k.egg-info/dependency_links.txt
q2k.egg-info/entry_points.txt
q2k.egg-info/not-zip-safe
q2k.egg-info/requires.txt
q2k.egg-info/top_level.txt
q2k/lib/action.h
q2k/lib/action_layer.h
q2k/lib/action_util.h
q2k/lib/audio.h
q2k/lib/backlight.h
q2k/lib/bootloader.h
q2k/lib/config_common.h
q2k/lib/debug.h
q2k/lib/dynamic_macro.h
q2k/lib/eeconfig.h
q2k/lib/frenchdev.h
q2k/lib/i2cmaster.h
q2k/lib/keycode.h
q2k/lib/keymap.h
q2k/lib/led.h
q2k/lib/matrix.h
q2k/lib/mousekey.h
q2k/lib/outputselect.h
q2k/lib/pointing_device.h
q2k/lib/print.h
q2k/lib/process_unicode.h
q2k/lib/quantum.h
q2k/lib/quantum_keycodes.h
q2k/lib/report.h
q2k/lib/rgblight.h
q2k/lib/ssd1306.h
q2k/lib/util.h
q2k/lib/version.h
q2k/lib/LUFA/Drivers/Peripheral/TWI.h
q2k/lib/keymap_extras/keymap_bepo.h