Metadata-Version: 1.1
Name: q2k
Version: 1.0.8a4
Summary: Convert AVR C based QMK keymap and matrix files to YAML Keyplus format
Home-page: https://github.com/2Cas/Q2K
Author: 2Cas
Author-email: 2Cas@seethis.link
License: MIT
Keywords: keyboard,usb,hid,qmk,keyplus
Platform: UNKNOWN
Classifier: Development Status :: 2 - Pre-Alpha
Classifier: Intended Audience :: Developers
Classifier: Programming Language :: Python :: 3 :: Only
Classifier: Programming Language :: Python :: 3.4
Classifier: Topic :: Software Development
Classifier: Topic :: Text Processing
Classifier: License :: OSI Approved :: MIT License
